gondrol/__init__.py
gondrol/introduction.py
gondrol-0.1.0.dist-info/METADATA
gondrol-0.1.0.dist-info/WHEEL
gondrol-0.1.0.dist-info/top_level.txt
gondrol-0.1.0.dist-info/RECORD
