Metadata-Version: 2.1
Name: gondrol
Version: 0.1.0
Summary: My Personal Python Packages
Author: Andri Ariyanto
Author-email: ariyant.andri@gmail.com
Keywords: python,gondrol
Classifier: Programming Language :: Python :: 3
Classifier: Operating System :: Unix
Classifier: Operating System :: MacOS :: MacOS X
Classifier: Operating System :: Microsoft :: Windows
